core/__init__.py
core/cel/__init__.py
core/cel/cel.py
core/cke/__init__.py
core/cke/cke.py
core/dsf/__init__.py
core/dsf/dsf.py
core/metadata/__init__.py
core/metadata/algorithmic_decoys.py
core/metadata/differential_decoys.py
core/metadata/integration.py
core/metadata/layered_format.py
core/metadata/selective_decoys.py
core/pcf/__init__.py
core/pcf/pcf.py
core/phe/__init__.py
core/phe/phe.py
core/profiles/__init__.py
core/profiles/adaptive_security.py
core/profiles/content_optimizers.py
core/profiles/profile_definitions.py
core/profiles/security_manager.py
core/profiles/security_profiles.py
core/state/__init__.py
core/state/metadata_utils.py
core/state/state.py
core/streaming/__init__.py
core/streaming/integration.py
core/streaming/optimized_decrypt.py
core/streaming/upfront_validation.py
interfaces/__init__.py
interfaces/api/__init__.py
interfaces/api/stc_api.py
interfaces/api/streaming_context.py
interfaces/cli/__init__.py
interfaces/cli/stc_cli.py
seigr_toolset_crypto-0.4.3.dist-info/licenses/LICENSE
utils/__init__.py
utils/dynamic_tlv.py
utils/math_primitives.py
utils/seigr_tlv.py
utils/tlv_format.py
seigr_toolset_crypto-0.4.3.dist-info/METADATA
seigr_toolset_crypto-0.4.3.dist-info/WHEEL
seigr_toolset_crypto-0.4.3.dist-info/entry_points.txt
seigr_toolset_crypto-0.4.3.dist-info/top_level.txt
seigr_toolset_crypto-0.4.3.dist-info/RECORD
