Metadata-Version: 2.4
Name: seigr-toolset-crypto
Version: 0.4.3
Summary: Post-classical cryptographic engine with automated security profiles and high-performance streaming
Home-page: https://github.com/Seigr-lab/SeigrToolsetCrypto
Author: Sergi Saldaña-Massó - Seigr Lab
Author-email: sergism@gmail.com
Project-URL: Homepage, https://github.com/Seigr-lab/SeigrToolsetCrypto
Project-URL: Documentation, https://github.com/Seigr-lab/SeigrToolsetCrypto/blob/main/docs/USAGE.md
Project-URL: Source, https://github.com/Seigr-lab/SeigrToolsetCrypto
Project-URL: Sponsor, https://github.com/sponsors/Seigr-lab
Project-URL: Changelog, https://github.com/Seigr-lab/SeigrToolsetCrypto/blob/main/docs/CHANGELOG.md
Keywords: cryptography seigr entropy security profiles adaptive streaming post-classical lattice-based
Classifier: Development Status :: 4 - Beta
Classifier: Intended Audience :: Developers
Classifier: Intended Audience :: End Users/Desktop
Classifier: Intended Audience :: Information Technology
Classifier: Topic :: Security :: Cryptography
Classifier: Topic :: Security
Classifier: Topic :: System :: Systems Administration
Classifier: Programming Language :: Python :: 3
Classifier: Programming Language :: Python :: 3.9
Classifier: Programming Language :: Python :: 3.10
Classifier: Programming Language :: Python :: 3.11
Classifier: Programming Language :: Python :: 3.12
Classifier: License :: Other/Proprietary License
Classifier: Operating System :: OS Independent
Classifier: Environment :: Console
Requires-Python: >=3.9
License-File: LICENSE
Requires-Dist: numpy>=1.24.0
Provides-Extra: dev
Requires-Dist: pytest>=7.0.0; extra == "dev"
Requires-Dist: pytest-cov>=4.0.0; extra == "dev"
Requires-Dist: coverage[toml]>=7.0.0; extra == "dev"
Dynamic: author
Dynamic: author-email
Dynamic: classifier
Dynamic: description
Dynamic: description-content-type
Dynamic: home-page
Dynamic: keywords
Dynamic: license-file
Dynamic: project-url
Dynamic: provides-extra
Dynamic: requires-dist
Dynamic: requires-python
Dynamic: summary
